mindthegap/AzureBlob.py
mindthegap/__init__.py
azure_blob_connector-0.0.13.dist-info/METADATA
azure_blob_connector-0.0.13.dist-info/WHEEL
azure_blob_connector-0.0.13.dist-info/top_level.txt
azure_blob_connector-0.0.13.dist-info/RECORD
